flake8_ruff/__init__.py
flake8_ruff/cli.py
flake8_ruff/rules.py
flake8_ruff_wrapper-0.4.0.dist-info/METADATA
flake8_ruff_wrapper-0.4.0.dist-info/WHEEL
flake8_ruff_wrapper-0.4.0.dist-info/entry_points.txt
flake8_ruff_wrapper-0.4.0.dist-info/licenses/LICENSE
flake8_ruff_wrapper-0.4.0.dist-info/RECORD
