Metadata-Version: 2.1
Name: flake8-ruff-wrapper
Version: 0.4.0
Summary: Invoke ruff using flake8 options
Project-URL: Homepage, https://github.com/fsouza/flake8-ruff-wrapper
License: ISC
License-File: LICENSE
Classifier: Environment :: Console
Classifier: Intended Audience :: Developers
Classifier: License :: OSI Approved :: ISC License (ISCL)
Classifier: Programming Language :: Python :: 3
Classifier: Programming Language :: Python :: 3 :: Only
Classifier: Programming Language :: Python :: 3.8
Classifier: Programming Language :: Python :: 3.9
Classifier: Programming Language :: Python :: 3.10
Classifier: Programming Language :: Python :: 3.11
Classifier: Programming Language :: Python :: 3.12
Classifier: Topic :: Software Development :: Quality Assurance
Requires-Python: >=3.8
Requires-Dist: flake8>=6.1.0
Requires-Dist: ruff>=0.0.292
Requires-Dist: toml>=0.10.2
